staticx/__init__.py
staticx/__main__.py
staticx/api.py
staticx/archive.py
staticx/assets.py
staticx/bcjfilter.py
staticx/constants.py
staticx/elf.py
staticx/errors.py
staticx/extract.py
staticx/utils.py
staticx/version.py
staticx/assets/debug/bootloader
staticx/assets/debug/libnssfix.so
staticx/assets/release/bootloader
staticx/assets/release/libnssfix.so
staticx/hooks/__init__.py
staticx/hooks/glibc.py
staticx/hooks/pyinstaller.py
staticx-0.14.1.dist-info/LICENSE.txt
staticx-0.14.1.dist-info/METADATA
staticx-0.14.1.dist-info/WHEEL
staticx-0.14.1.dist-info/entry_points.txt
staticx-0.14.1.dist-info/top_level.txt
staticx-0.14.1.dist-info/RECORD
