Metadata-Version: 2.1
Name: staticx
Version: 0.14.1
Summary: Build static self-extracting app from dynamic executable
Home-page: https://github.com/JonathonReinhart/staticx
Author: Jonathon Reinhart
Author-email: jonathon.reinhart@gmail.com
License: GPL v2 with special exception allowing StaticX to build and distribute non-free programs
Classifier: Development Status :: 3 - Alpha
Classifier: Environment :: Console
Classifier: Intended Audience :: Developers
Classifier: License :: OSI Approved :: GNU General Public License v2 or later (GPLv2+)
Classifier: Natural Language :: English
Classifier: Operating System :: POSIX :: Linux
Classifier: Programming Language :: Python :: 3
Classifier: Programming Language :: Python :: 3.7
Classifier: Programming Language :: Python :: 3.8
Classifier: Programming Language :: Python :: 3.9
Classifier: Programming Language :: Python :: 3.10
Classifier: Programming Language :: Python :: 3.11
Classifier: Programming Language :: Python :: Implementation :: CPython
Classifier: Topic :: Software Development :: Build Tools
Requires-Python: >=3.7
License-File: LICENSE.txt
Requires-Dist: pyelftools
